{
  "tenantId": "uk",
  "moduleName": "tenant",
  "citywiseconfig": [
    {
      "config": "ptCitizenPayButton",
      "enabledCities": [
        "uk.haldwani",
        "uk.dehradun",
        "uk.ramnagar",
        "uk.mussorie",
        "uk.kaladhungi",
        "uk.doiwala",
        "uk.uttarakhand"
      ]
    },
    {
      "config": "ptSendUpdateSMS",
      "enabledCities": [
        "uk.haldwani",
        "uk.dehradun",
        "uk.ramnagar",
        "uk.mussorie",
        "uk.kaladhungi",
        "uk.doiwala",
        "uk.uttarakhand"
      ]
    },
    {
      "config": "ptCalculateRebateAndPenalty",
      "enabledCities": [
        "uk.haldwani",
        "uk.dehradun",
        "uk.ramnagar",
        "uk.mussorie",
        "uk.kaladhungi",
        "uk.doiwala",
        "uk.uttarakhand"
      ]
    }
  ]
}
